bitvaluta_rpc/__init__.py
bitvaluta_rpc/bitvaluta_rpc.py
bitvaluta_rpc-1.31.dist-info/LICENSE
bitvaluta_rpc-1.31.dist-info/METADATA
bitvaluta_rpc-1.31.dist-info/WHEEL
bitvaluta_rpc-1.31.dist-info/top_level.txt
bitvaluta_rpc-1.31.dist-info/RECORD
