Metadata-Version: 2.1
Name: bitvaluta-rpc
Version: 1.31
Summary: Library to communicate with bitvaluta daemon via JSON-RPC protocol.
Home-page: https://github.com/justluce/bitvaluta_rpc
Author: justluce
Author-email: support@justinluce.com
License: MIT
Keywords: bitvaluta,json-rpc,cryptocurrency,blockchain
Platform: any
Classifier: Development Status :: 4 - Beta
Classifier: Intended Audience :: Financial and Insurance Industry
Classifier: Programming Language :: Python
Classifier: Operating System :: OS Independent
Classifier: Natural Language :: English
Classifier: License :: OSI Approved :: MIT License
Requires-Dist: requests
